Metadata-Version: 2.1
Name: swiftscribe_templater
Version: 1.2
Summary: Generate documents based on a template and populate the tokens within the document.
Home-page: https://github.com/MrNate592/docscribe-templater/tree/master
Author: Nathan Budhu
Author-email: nathanbudhu@gmail.com
Classifier: Programming Language :: Python :: 3
Classifier: License :: OSI Approved :: MIT License
Classifier: Operating System :: OS Independent
Requires-Dist: nltk
Requires-Dist: python-docx
Requires-Dist: setuptools
